asyncurban/__init__.py
asyncurban/errors.py
asyncurban/urbandictionary.py
asyncurban/word.py
asyncurban-0.3.3.dist-info/DESCRIPTION.rst
asyncurban-0.3.3.dist-info/METADATA
asyncurban-0.3.3.dist-info/RECORD
asyncurban-0.3.3.dist-info/WHEEL
asyncurban-0.3.3.dist-info/metadata.json
asyncurban-0.3.3.dist-info/top_level.txt
