Metadata-Version: 2.0
Name: asyncurban
Version: 0.3.3
Summary: An asynchronous wrapper around the UrbanDictionary API.
Home-page: https://github.com/naught0/asyncurban
Author: James E
Author-email: naught0@github.com
License: MIT
Keywords: dictionary,urban,urbandictionary,define
Platform: UNKNOWN
Classifier: Programming Language :: Python :: 3.6
Requires-Python: >=3.5
Requires-Dist: aiohttp (>=2.3.7)
